openalexnetwork/__init__.py
openalexnetwork/crawler.py
openalexnetwork/logging_setup.py
openalexnetwork/network.py
openalexnetwork/utils/__init__.py
openalexnetwork/utils/iterators.py
openalexnetwork/utils/utils.py
openalexnetwork-0.1.6.dist-info/METADATA
openalexnetwork-0.1.6.dist-info/WHEEL
openalexnetwork-0.1.6.dist-info/RECORD
