Metadata-Version: 2.3
Name: openalexnetwork
Version: 0.1.6
Summary: Module to build citation networks with OpenAlex
Author: Reza Tabrizi
Author-email: rtabrizi03@gmail.com
Requires-Python: >=3.10,<4.0
Classifier: Programming Language :: Python :: 3
Classifier: Programming Language :: Python :: 3.10
Classifier: Programming Language :: Python :: 3.11
Classifier: Programming Language :: Python :: 3.12
Classifier: Programming Language :: Python :: 3.13
Requires-Dist: matplotlib (>=3.10.0,<4.0.0)
Requires-Dist: openalexnet (>=0.1.2,<0.2.0)
Requires-Dist: pycairo (>=1.27.0,<2.0.0)
Requires-Dist: scholarly (>=1.7.11,<2.0.0)
